{
    "name": "Notfall-Licht_v01",
    "description": "",
    "dependencies": {
        "core": "*",
        "v1": "*",
        "lichtsensor-events": "github:gunst-at-hvh/pxt-lichtsensor-events#44e9df5e2b00d06f4ec18aec86e64b57471deccc"
    },
    "files": [
        "main.blocks",
        "main.ts",
        "README.md"
    ],
    "testFiles": [
        "test.ts"
    ],
    "targetVersions": {
        "target": "8.1.11",
        "targetId": "calliopemini"
    },
    "supportedTargets": [
        "calliopemini"
    ],
    "preferredEditor": "blocksprj"
}
